brainfuck/__init__.py
brainfuck/command_line.py
brainfuck/contrib/__init__.py
brainfuck/contrib/execution.py
brainfuck/contrib/pyast.py
brainfuck/parsing/__init__.py
brainfuck/parsing/ast.py
brainfuck/parsing/parser.py
brainfuck/parsing/tokenizer.py
brainfuck_venomlab-0.1.1.dist-info/LICENSE
brainfuck_venomlab-0.1.1.dist-info/METADATA
brainfuck_venomlab-0.1.1.dist-info/WHEEL
brainfuck_venomlab-0.1.1.dist-info/entry_points.txt
brainfuck_venomlab-0.1.1.dist-info/top_level.txt
brainfuck_venomlab-0.1.1.dist-info/RECORD
